redmail/__init__.py
redmail/_version.py
redmail/log.py
redmail/py.typed
redmail/utils.py
redmail/email/__init__.py
redmail/email/attachment.py
redmail/email/body.py
redmail/email/envs.py
redmail/email/sender.py
redmail/email/utils.py
redmail/email/templates/html/table/custom.html
redmail/email/templates/html/table/modest.html
redmail/email/templates/html/table/notebook-like.html
redmail/email/templates/text/table/pandas.txt
redmail/models/__init__.py
redmail/models/address.py
redmail/models/system.py
redmail/test/__init__.py
redmail/test/conftest.py
redmail/test/pytest.ini
redmail/test/test_deprecated.py
redmail/test/test_models.py
redmail/test/test_utils.py
redmail/test/email/__init__.py
redmail/test/email/test_attachments.py
redmail/test/email/test_body.py
redmail/test/email/test_cookbook.py
redmail/test/email/test_headers.py
redmail/test/email/test_inline_media.py
redmail/test/email/test_send.py
redmail/test/email/test_structure.py
redmail/test/email/test_template.py
redmail/test/helpers/__init__.py
redmail/test/helpers/convert.py
redmail/test/helpers/resources.py
redmail/test/log/__init__.py
redmail/test/log/conftest.py
redmail/test/log/test_construct.py
redmail/test/log/test_handler.py
redmail/test/log/test_handler_multi.py
redmail/test/test_files/dummy.png
redmail-0.6.0.dist-info/LICENSE
redmail-0.6.0.dist-info/METADATA
redmail-0.6.0.dist-info/WHEEL
redmail-0.6.0.dist-info/top_level.txt
redmail-0.6.0.dist-info/RECORD
