Metadata-Version: 2.1
Name: redmail
Version: 0.6.0
Summary: Email sending library
Author-email: Mikael Koli <koli.mikael@gmail.com>
License: MIT License
Project-URL: Homepage, https://github.com/Miksus/red-mail
Project-URL: Documentation, https://red-mail.readthedocs.io
Project-URL: Funding, https://github.com/sponsors/Miksus
Project-URL: Source, https://github.com/Miksus/red-mail
Project-URL: Changelog, https://red-mail.readthedocs.io/en/stable/versions.html
Classifier: Topic :: Communications :: Email
Classifier: Operating System :: OS Independent
Classifier: License :: OSI Approved :: MIT License
Classifier: Programming Language :: Python :: 3
Classifier: Programming Language :: Python :: 3.6
Classifier: Programming Language :: Python :: 3.7
Classifier: Programming Language :: Python :: 3.8
Classifier: Programming Language :: Python :: 3.9
Classifier: Programming Language :: Python :: 3.10
Classifier: Programming Language :: Python :: 3.11
Classifier: Intended Audience :: Developers
Classifier: Intended Audience :: Customer Service
Classifier: Intended Audience :: Financial and Insurance Industry
Requires-Python: >=3.6
Provides-Extra: test
Provides-Extra: docs
Provides-Extra: style
License-File: LICENSE
